aara/__init__.py
aara/aara.py
aara-0.0.7.dist-info/METADATA
aara-0.0.7.dist-info/WHEEL
aara-0.0.7.dist-info/entry_points.txt
aara-0.0.7.dist-info/licenses/LICENSE
aara-0.0.7.dist-info/RECORD
