Metadata-Version: 2.4
Name: aara
Version: 0.0.7
Summary: ArXiv Reader App
Project-URL: Homepage, https://github.com/jsnguyen/aara
Author: Jayke Nguyen
License-File: LICENSE
Requires-Python: >=3.10
Requires-Dist: aiohttp>=3.12.15
Requires-Dist: beautifulsoup4>=4.13.5
Requires-Dist: textual>=6.1.0
